gitplier/__init__.py
gitplier/_base.py
gitplier/_commit.py
gitplier/_config.py
gitplier/_constants.py
gitplier/_diff.py
gitplier/_exceptions.py
gitplier/_execute.py
gitplier/_remote.py
gitplier/_repository.py
gitplier/_status.py
gitplier/_tag.py
gitplier/_utils.py
gitplier/kernel/__init__.py
gitplier/kernel/_commit.py
gitplier/kernel/_repository.py
gitplier-1.1.dist-info/METADATA
gitplier-1.1.dist-info/WHEEL
gitplier-1.1.dist-info/licenses/LICENSE.md
gitplier-1.1.dist-info/RECORD
