Metadata-Version: 2.4
Name: gitplier
Version: 1.1
Summary: A Python library for easy and performant querying and parsing of Git repositories.
Project-URL: Homepage, https://gitlab.com/gitplier/gitplier
Author-email: Jiri Benc <jbenc@redhat.com>
License-Expression: LGPL-2.1-or-later
License-File: LICENSE.md
Classifier: Operating System :: POSIX :: Linux
Classifier: Programming Language :: Python :: 3
Requires-Python: >=3.9
